bastion/__init__.py
bastion/__main__.py
bastion/cli.py
bastion/config.py
bastion/git_utils.py
bastion/models.py
bastion/py.typed
bastion/scanner.py
bastion/analyzers/__init__.py
bastion/analyzers/base.py
bastion/analyzers/dataflow_analyzers.py
bastion/analyzers/framework_analyzers.py
bastion/analyzers/prompt_analyzers.py
bastion/analyzers/registry.py
bastion/analyzers/security_analyzers.py
bastion/parsers/__init__.py
bastion/parsers/base.py
bastion/parsers/registry.py
bastion/parsers/utils.py
bastion/reporters/__init__.py
bastion/reporters/base.py
bastion/reporters/factory.py
bastion/reporters/html.py
bastion/reporters/json_reporter.py
bastion/reporters/sarif.py
bastion/reporters/text.py
bastion/rules/__init__.py
bastion/rules/builtin_rules.py
bastion/rules/registry.py
bastion/taint/__init__.py
bastion/taint/analyzer.py
bastion/taint/models.py
bastion/taint/tracker.py
bastion/utils/__init__.py
bastion/utils/helpers.py
bastion_llm-0.1.0.dist-info/METADATA
bastion_llm-0.1.0.dist-info/WHEEL
bastion_llm-0.1.0.dist-info/entry_points.txt
bastion_llm-0.1.0.dist-info/licenses/LICENSE
bastion_llm-0.1.0.dist-info/RECORD
