Metadata-Version: 2.4
Name: bastion-llm
Version: 0.1.0
Summary: A pre-commit security scanner that detects prompt injection vulnerabilities in LLM application codebases through static analysis
Project-URL: Homepage, https://github.com/en-yao/bastion
Project-URL: Documentation, https://github.com/en-yao/bastion#readme
Project-URL: Repository, https://github.com/en-yao/bastion
Project-URL: Issues, https://github.com/en-yao/bastion/issues
Author: Bastion Contributors
License-Expression: MIT
License-File: LICENSE
Keywords: llm,pre-commit,prompt-injection,sast,security,static-analysis
Classifier: Development Status :: 3 - Alpha
Classifier: Environment :: Console
Classifier: Intended Audience :: Developers
Classifier: License :: OSI Approved :: MIT License
Classifier: Operating System :: OS Independent
Classifier: Programming Language :: Python :: 3
Classifier: Programming Language :: Python :: 3.11
Classifier: Programming Language :: Python :: 3.12
Classifier: Topic :: Security
Classifier: Topic :: Software Development :: Quality Assurance
Requires-Python: >=3.11
Requires-Dist: click>=8.1.0
Requires-Dist: pathspec>=0.12.0
Requires-Dist: pyyaml>=6.0
Requires-Dist: rich>=13.0.0
Requires-Dist: tree-sitter-javascript>=0.21.0
Requires-Dist: tree-sitter-python>=0.21.0
Requires-Dist: tree-sitter-typescript>=0.21.0
Requires-Dist: tree-sitter>=0.21.0
Provides-Extra: dev
Requires-Dist: hypothesis>=6.0.0; extra == 'dev'
Requires-Dist: mypy>=1.0.0; extra == 'dev'
Requires-Dist: pytest-cov>=4.0.0; extra == 'dev'
Requires-Dist: pytest>=7.0.0; extra == 'dev'
Requires-Dist: ruff>=0.1.0; extra == 'dev'
Requires-Dist: types-pyyaml>=6.0.0; extra == 'dev'
